{
	"$schema": "http://schema.management.azure.com/schemas/2015-01-01/deploymentTemplate.json#",
	"contentVersion": "1.0.0.0",
	"parameters": {
		"factoryName": {
			"type": "string",
			"metadata": "Data Factory name",
			"defaultValue": "datafactory-atj"
		},
		"AzureSqlDatabase1_password": {
			"type": "secureString",
			"metadata": "Secure string for 'password' of 'AzureSqlDatabase1'"
		},
		"DataLakeStorage_accountKey": {
			"type": "secureString",
			"metadata": "Secure string for 'accountKey' of 'DataLakeStorage'"
		},
		"MySQLdb_password": {
			"type": "secureString",
			"metadata": "Secure string for 'password' of 'MySQLdb'"
		},
		"AzureSqlDatabase1_properties_typeProperties_server": {
			"type": "string",
			"defaultValue": "trainserversuh.database.windows.net"
		},
		"AzureSqlDatabase1_properties_typeProperties_database": {
			"type": "string",
			"defaultValue": "PracticeDB"
		},
		"AzureSqlDatabase1_properties_typeProperties_userName": {
			"type": "string",
			"defaultValue": "sqladmin"
		},
		"DataLakeStorage_properties_typeProperties_url": {
			"type": "string",
			"defaultValue": "https://storageaccatj.dfs.core.windows.net/"
		},
		"GithubDatasets_properties_typeProperties_url": {
			"type": "string",
			"defaultValue": "https://raw.githubusercontent.com"
		},
		"MySQLdb_properties_typeProperties_server": {
			"type": "string",
			"defaultValue": "trainingdbserv.database.windows.net"
		},
		"MySQLdb_properties_typeProperties_database": {
			"type": "string",
			"defaultValue": "training_DB"
		},
		"MySQLdb_properties_typeProperties_userName": {
			"type": "string",
			"defaultValue": "sqladmin"
		}
	},
	"variables": {
		"factoryId": "[concat('Microsoft.DataFactory/factories/', parameters('factoryName'))]"
	},
	"resources": [
		{
			"name": "[concat(parameters('factoryName'), '/AzureSqlDatabase1')]",
			"type": "Microsoft.DataFactory/factories/linkedServices",
			"apiVersion": "2018-06-01",
			"properties": {
				"annotations": [],
				"type": "AzureSqlDatabase",
				"typeProperties": {
					"server": "[parameters('AzureSqlDatabase1_properties_typeProperties_server')]",
					"database": "[parameters('AzureSqlDatabase1_properties_typeProperties_database')]",
					"encrypt": "mandatory",
					"trustServerCertificate": true,
					"authenticationType": "SQL",
					"userName": "[parameters('AzureSqlDatabase1_properties_typeProperties_userName')]",
					"password": {
						"type": "SecureString",
						"value": "[parameters('AzureSqlDatabase1_password')]"
					}
				}
			},
			"dependsOn": []
		},
		{
			"name": "[concat(parameters('factoryName'), '/DataLakeStorage')]",
			"type": "Microsoft.DataFactory/factories/linkedServices",
			"apiVersion": "2018-06-01",
			"properties": {
				"annotations": [],
				"type": "AzureBlobFS",
				"typeProperties": {
					"url": "[parameters('DataLakeStorage_properties_typeProperties_url')]",
					"accountKey": {
						"type": "SecureString",
						"value": "[parameters('DataLakeStorage_accountKey')]"
					}
				}
			},
			"dependsOn": []
		},
		{
			"name": "[concat(parameters('factoryName'), '/GithubDatasets')]",
			"type": "Microsoft.DataFactory/factories/linkedServices",
			"apiVersion": "2018-06-01",
			"properties": {
				"annotations": [],
				"type": "HttpServer",
				"typeProperties": {
					"url": "[parameters('GithubDatasets_properties_typeProperties_url')]",
					"enableServerCertificateValidation": true,
					"authenticationType": "Anonymous"
				}
			},
			"dependsOn": []
		},
		{
			"name": "[concat(parameters('factoryName'), '/MySQLdb')]",
			"type": "Microsoft.DataFactory/factories/linkedServices",
			"apiVersion": "2018-06-01",
			"properties": {
				"annotations": [],
				"type": "AzureSqlDatabase",
				"typeProperties": {
					"server": "[parameters('MySQLdb_properties_typeProperties_server')]",
					"database": "[parameters('MySQLdb_properties_typeProperties_database')]",
					"encrypt": "mandatory",
					"trustServerCertificate": true,
					"authenticationType": "SQL",
					"userName": "[parameters('MySQLdb_properties_typeProperties_userName')]",
					"password": {
						"type": "SecureString",
						"value": "[parameters('MySQLdb_password')]"
					}
				}
			},
			"dependsOn": []
		},
		{
			"name": "[concat(parameters('factoryName'), '/AzureSqlTable2')]",
			"type": "Microsoft.DataFactory/factories/datasets",
			"apiVersion": "2018-06-01",
			"properties": {
				"linkedServiceName": {
					"referenceName": "AzureSqlDatabase1",
					"type": "LinkedServiceReference"
				},
				"parameters": {
					"TableSchema": {
						"type": "string"
					},
					"TableName": {
						"type": "string"
					}
				},
				"annotations": [],
				"type": "AzureSqlTable",
				"schema": [],
				"typeProperties": {
					"schema": "dbo",
					"table": {
						"value": "@dataset().TableName",
						"type": "Expression"
					}
				}
			},
			"dependsOn": [
				"[concat(variables('factoryId'), '/linkedServices/AzureSqlDatabase1')]"
			]
		},
		{
			"name": "[concat(parameters('factoryName'), '/DSGetParam')]",
			"type": "Microsoft.DataFactory/factories/datasets",
			"apiVersion": "2018-06-01",
			"properties": {
				"linkedServiceName": {
					"referenceName": "DataLakeStorage",
					"type": "LinkedServiceReference"
				},
				"annotations": [],
				"type": "Json",
				"typeProperties": {
					"location": {
						"type": "AzureBlobFSLocation",
						"fileName": "git.json",
						"fileSystem": "parameters"
					}
				},
				"schema": {
					"type": "object",
					"properties": {
						"RelativeUrl": {
							"type": "string"
						},
						"SinkFolder": {
							"type": "string"
						},
						"SinkFileName": {
							"type": "string"
						}
					}
				}
			},
			"dependsOn": [
				"[concat(variables('factoryId'), '/linkedServices/DataLakeStorage')]"
			]
		},
		{
			"name": "[concat(parameters('factoryName'), '/DSGit_Dyn')]",
			"type": "Microsoft.DataFactory/factories/datasets",
			"apiVersion": "2018-06-01",
			"properties": {
				"linkedServiceName": {
					"referenceName": "GithubDatasets",
					"type": "LinkedServiceReference"
				},
				"parameters": {
					"RelativeUrl": {
						"type": "string"
					}
				},
				"annotations": [],
				"type": "DelimitedText",
				"typeProperties": {
					"location": {
						"type": "HttpServerLocation",
						"relativeUrl": {
							"value": "@dataset().RelativeUrl",
							"type": "Expression"
						}
					},
					"columnDelimiter": ",",
					"escapeChar": "\\",
					"firstRowAsHeader": true,
					"quoteChar": "\""
				},
				"schema": []
			},
			"dependsOn": [
				"[concat(variables('factoryId'), '/linkedServices/GithubDatasets')]"
			]
		},
		{
			"name": "[concat(parameters('factoryName'), '/DS_Http')]",
			"type": "Microsoft.DataFactory/factories/datasets",
			"apiVersion": "2018-06-01",
			"properties": {
				"linkedServiceName": {
					"referenceName": "GithubDatasets",
					"type": "LinkedServiceReference"
				},
				"annotations": [],
				"type": "DelimitedText",
				"typeProperties": {
					"location": {
						"type": "HttpServerLocation",
						"relativeUrl": "anshlambaoldgit/Adventure-Works-Data-Engineering-Project/refs/heads/main/Data/AdventureWorks_Products.csv"
					},
					"columnDelimiter": ",",
					"escapeChar": "\\",
					"firstRowAsHeader": true,
					"quoteChar": "\""
				},
				"schema": []
			},
			"dependsOn": [
				"[concat(variables('factoryId'), '/linkedServices/GithubDatasets')]"
			]
		},
		{
			"name": "[concat(parameters('factoryName'), '/DS_sinkDyn')]",
			"type": "Microsoft.DataFactory/factories/datasets",
			"apiVersion": "2018-06-01",
			"properties": {
				"linkedServiceName": {
					"referenceName": "DataLakeStorage",
					"type": "LinkedServiceReference"
				},
				"parameters": {
					"SinkFolder": {
						"type": "string"
					},
					"SinkFileName": {
						"type": "string"
					}
				},
				"annotations": [],
				"type": "DelimitedText",
				"typeProperties": {
					"location": {
						"type": "AzureBlobFSLocation",
						"fileName": {
							"value": "@dataset().SinkFileName",
							"type": "Expression"
						},
						"folderPath": {
							"value": "@dataset().SinkFolder",
							"type": "Expression"
						},
						"fileSystem": "bronze"
					},
					"columnDelimiter": ",",
					"escapeChar": "\\",
					"firstRowAsHeader": true,
					"quoteChar": "\""
				},
				"schema": []
			},
			"dependsOn": [
				"[concat(variables('factoryId'), '/linkedServices/DataLakeStorage')]"
			]
		},
		{
			"name": "[concat(parameters('factoryName'), '/LookUpMetaData')]",
			"type": "Microsoft.DataFactory/factories/datasets",
			"apiVersion": "2018-06-01",
			"properties": {
				"linkedServiceName": {
					"referenceName": "MySQLdb",
					"type": "LinkedServiceReference"
				},
				"annotations": [],
				"type": "AzureSqlTable",
				"schema": [
					{
						"name": "ID",
						"type": "int",
						"precision": 10
					},
					{
						"name": "TableName",
						"type": "varchar"
					},
					{
						"name": "LastModifiedDate",
						"type": "date"
					}
				],
				"typeProperties": {
					"schema": "Cntrl",
					"table": "Metadata"
				}
			},
			"dependsOn": [
				"[concat(variables('factoryId'), '/linkedServices/MySQLdb')]"
			]
		},
		{
			"name": "[concat(parameters('factoryName'), '/SinkTableinfo')]",
			"type": "Microsoft.DataFactory/factories/datasets",
			"apiVersion": "2018-06-01",
			"properties": {
				"linkedServiceName": {
					"referenceName": "MySQLdb",
					"type": "LinkedServiceReference"
				},
				"annotations": [],
				"type": "AzureSqlTable",
				"schema": [],
				"typeProperties": {
					"schema": "Landing",
					"table": "VM_SORDERS"
				}
			},
			"dependsOn": [
				"[concat(variables('factoryId'), '/linkedServices/MySQLdb')]"
			]
		},
		{
			"name": "[concat(parameters('factoryName'), '/Assignment-1')]",
			"type": "Microsoft.DataFactory/factories/pipelines",
			"apiVersion": "2018-06-01",
			"properties": {
				"activities": [
					{
						"name": "Lookup1",
						"type": "Lookup",
						"dependsOn": [],
						"policy": {
							"timeout": "0.12:00:00",
							"retry": 0,
							"retryIntervalInSeconds": 30,
							"secureOutput": false,
							"secureInput": false
						},
						"userProperties": [],
						"typeProperties": {
							"source": {
								"type": "AzureSqlSource",
								"sqlReaderQuery": "Select * from Cntrl.Metadata",
								"queryTimeout": "02:00:00",
								"partitionOption": "None"
							},
							"dataset": {
								"referenceName": "LookUpMetaData",
								"type": "DatasetReference",
								"parameters": {}
							},
							"firstRowOnly": false
						}
					},
					{
						"name": "ForEach1",
						"type": "ForEach",
						"dependsOn": [
							{
								"activity": "TruncateLanding",
								"dependencyConditions": [
									"Succeeded"
								]
							}
						],
						"userProperties": [],
						"typeProperties": {
							"items": {
								"value": "@activity('Lookup1').output.value",
								"type": "Expression"
							},
							"isSequential": true,
							"activities": [
								{
									"name": "Copy data1",
									"type": "Copy",
									"dependsOn": [],
									"policy": {
										"timeout": "0.12:00:00",
										"retry": 0,
										"retryIntervalInSeconds": 30,
										"secureOutput": false,
										"secureInput": false
									},
									"userProperties": [],
									"typeProperties": {
										"source": {
											"type": "AzureSqlSource",
											"additionalColumns": [
												{
													"name": "table_code",
													"value": {
														"value": "@item().TableCode",
														"type": "Expression"
													}
												}
											],
											"sqlReaderQuery": {
												"value": "@concat('SELECT * FROM ', item().TableName,' where UpdatedAt > ''', formatDateTime(item().LastModifiedDate, 'yyyy-MM-dd HH:mm:ss.fff'), '''')",
												"type": "Expression"
											},
											"queryTimeout": "02:00:00",
											"partitionOption": "None"
										},
										"sink": {
											"type": "AzureSqlSink",
											"writeBehavior": "insert",
											"sqlWriterUseTableLock": false,
											"disableMetricsCollection": false
										},
										"enableStaging": false,
										"translator": {
											"type": "TabularTranslator",
											"typeConversion": true,
											"typeConversionSettings": {
												"allowDataTruncation": true,
												"treatBooleanAsNumber": false
											}
										}
									},
									"inputs": [
										{
											"referenceName": "AzureSqlTable2",
											"type": "DatasetReference",
											"parameters": {
												"TableSchema": "dbo",
												"TableName": {
													"value": "@item().TableName",
													"type": "Expression"
												}
											}
										}
									],
									"outputs": [
										{
											"referenceName": "SinkTableinfo",
											"type": "DatasetReference",
											"parameters": {}
										}
									]
								},
								{
									"name": "LogRecordsMoved",
									"type": "Script",
									"dependsOn": [
										{
											"activity": "Copy data1",
											"dependencyConditions": [
												"Succeeded"
											]
										}
									],
									"policy": {
										"timeout": "0.12:00:00",
										"retry": 0,
										"retryIntervalInSeconds": 30,
										"secureOutput": false,
										"secureInput": false
									},
									"userProperties": [],
									"linkedServiceName": {
										"referenceName": "MySQLdb",
										"type": "LinkedServiceReference"
									},
									"typeProperties": {
										"scripts": [
											{
												"type": "Query",
												"text": {
													"value": "@concat('UPDATE Cntrl.Metadata SET RowsCopied = ', string(activity('Copy data1').output.rowsCopied), ' WHERE TableCode = ''', item().TableCode, '''')\n\n",
													"type": "Expression"
												}
											}
										],
										"scriptBlockExecutionTimeout": "02:00:00"
									}
								}
							]
						}
					},
					{
						"name": "PushtoMART",
						"type": "SqlServerStoredProcedure",
						"dependsOn": [
							{
								"activity": "ForEach1",
								"dependencyConditions": [
									"Succeeded"
								]
							}
						],
						"policy": {
							"timeout": "0.12:00:00",
							"retry": 0,
							"retryIntervalInSeconds": 30,
							"secureOutput": false,
							"secureInput": false
						},
						"userProperties": [],
						"typeProperties": {
							"storedProcedureName": "[[Cntrl].[procMartSORDERS]"
						},
						"linkedServiceName": {
							"referenceName": "MySQLdb",
							"type": "LinkedServiceReference"
						}
					},
					{
						"name": "ForEach2",
						"type": "ForEach",
						"dependsOn": [
							{
								"activity": "PushtoMART",
								"dependencyConditions": [
									"Succeeded"
								]
							}
						],
						"userProperties": [],
						"typeProperties": {
							"items": {
								"value": "@activity('Lookup1').output.value",
								"type": "Expression"
							},
							"isSequential": true,
							"activities": [
								{
									"name": "UpdateLastModified",
									"type": "SqlServerStoredProcedure",
									"dependsOn": [],
									"policy": {
										"timeout": "0.12:00:00",
										"retry": 0,
										"retryIntervalInSeconds": 30,
										"secureOutput": false,
										"secureInput": false
									},
									"userProperties": [],
									"typeProperties": {
										"storedProcedureName": "[[Cntrl].[Update_LastLoadedAt]",
										"storedProcedureParameters": {
											"BranchCode": {
												"value": {
													"value": "@item().TableCode",
													"type": "Expression"
												},
												"type": "String"
											}
										}
									},
									"linkedServiceName": {
										"referenceName": "MySQLdb",
										"type": "LinkedServiceReference"
									}
								}
							]
						}
					},
					{
						"name": "TruncateLanding",
						"type": "Script",
						"dependsOn": [
							{
								"activity": "Lookup1",
								"dependencyConditions": [
									"Succeeded"
								]
							}
						],
						"policy": {
							"timeout": "0.12:00:00",
							"retry": 0,
							"retryIntervalInSeconds": 30,
							"secureOutput": false,
							"secureInput": false
						},
						"userProperties": [],
						"linkedServiceName": {
							"referenceName": "MySQLdb",
							"type": "LinkedServiceReference"
						},
						"typeProperties": {
							"scripts": [
								{
									"type": "Query",
									"text": "Truncate Table Landing.VM_SORDERS"
								}
							],
							"scriptBlockExecutionTimeout": "02:00:00"
						}
					}
				],
				"policy": {
					"elapsedTimeMetric": {}
				},
				"annotations": [],
				"lastPublishTime": "2025-05-27T11:44:06Z"
			},
			"dependsOn": [
				"[concat(variables('factoryId'), '/datasets/LookUpMetaData')]",
				"[concat(variables('factoryId'), '/linkedServices/MySQLdb')]",
				"[concat(variables('factoryId'), '/datasets/AzureSqlTable2')]",
				"[concat(variables('factoryId'), '/datasets/SinkTableinfo')]"
			]
		},
		{
			"name": "[concat(parameters('factoryName'), '/Practice-A')]",
			"type": "Microsoft.DataFactory/factories/pipelines",
			"apiVersion": "2018-06-01",
			"properties": {
				"activities": [
					{
						"name": "ForEachGit",
						"type": "ForEach",
						"dependsOn": [
							{
								"activity": "LookupGitDSMetadata",
								"dependencyConditions": [
									"Succeeded"
								]
							}
						],
						"userProperties": [],
						"typeProperties": {
							"items": {
								"value": "@activity('LookupGitDSMetadata').output.value",
								"type": "Expression"
							},
							"isSequential": true,
							"activities": [
								{
									"name": "DynamicRawDS",
									"type": "Copy",
									"dependsOn": [],
									"policy": {
										"timeout": "0.12:00:00",
										"retry": 0,
										"retryIntervalInSeconds": 30,
										"secureOutput": false,
										"secureInput": false
									},
									"userProperties": [],
									"typeProperties": {
										"source": {
											"type": "DelimitedTextSource",
											"storeSettings": {
												"type": "HttpReadSettings",
												"requestMethod": "GET"
											},
											"formatSettings": {
												"type": "DelimitedTextReadSettings"
											}
										},
										"sink": {
											"type": "DelimitedTextSink",
											"storeSettings": {
												"type": "AzureBlobFSWriteSettings"
											},
											"formatSettings": {
												"type": "DelimitedTextWriteSettings",
												"quoteAllText": true,
												"fileExtension": ".txt"
											}
										},
										"enableStaging": false,
										"translator": {
											"type": "TabularTranslator",
											"typeConversion": true,
											"typeConversionSettings": {
												"allowDataTruncation": true,
												"treatBooleanAsNumber": false
											}
										}
									},
									"inputs": [
										{
											"referenceName": "DSGit_Dyn",
											"type": "DatasetReference",
											"parameters": {
												"RelativeUrl": {
													"value": "@item().RelativeUrl",
													"type": "Expression"
												}
											}
										}
									],
									"outputs": [
										{
											"referenceName": "DS_sinkDyn",
											"type": "DatasetReference",
											"parameters": {
												"SinkFolder": {
													"value": "@item().SinkFolder",
													"type": "Expression"
												},
												"SinkFileName": {
													"value": "@item().SinkFileName",
													"type": "Expression"
												}
											}
										}
									]
								}
							]
						}
					},
					{
						"name": "LookupGitDSMetadata",
						"type": "Lookup",
						"dependsOn": [],
						"policy": {
							"timeout": "0.12:00:00",
							"retry": 0,
							"retryIntervalInSeconds": 30,
							"secureOutput": false,
							"secureInput": false
						},
						"userProperties": [],
						"typeProperties": {
							"source": {
								"type": "JsonSource",
								"storeSettings": {
									"type": "AzureBlobFSReadSettings",
									"recursive": true,
									"enablePartitionDiscovery": false
								},
								"formatSettings": {
									"type": "JsonReadSettings"
								}
							},
							"dataset": {
								"referenceName": "DSGetParam",
								"type": "DatasetReference",
								"parameters": {}
							},
							"firstRowOnly": false
						}
					}
				],
				"policy": {
					"elapsedTimeMetric": {}
				},
				"annotations": [],
				"lastPublishTime": "2025-05-28T06:49:55Z"
			},
			"dependsOn": [
				"[concat(variables('factoryId'), '/datasets/DSGetParam')]",
				"[concat(variables('factoryId'), '/datasets/DSGit_Dyn')]",
				"[concat(variables('factoryId'), '/datasets/DS_sinkDyn')]"
			]
		}
	]
}